ctclass/__init__.py
ign_ctclass-0.0.0.dist-info/METADATA
ign_ctclass-0.0.0.dist-info/WHEEL
ign_ctclass-0.0.0.dist-info/top_level.txt
ign_ctclass-0.0.0.dist-info/RECORD
